.gitignore
LICENSE.txt
README
README.md
bibfix.py
setup.py
bibfix.egg-info/PKG-INFO
bibfix.egg-info/SOURCES.txt
bibfix.egg-info/dependency_links.txt
bibfix.egg-info/entry_points.txt
bibfix.egg-info/requires.txt
bibfix.egg-info/top_level.txt