Metadata-Version: 1.0
Name: bibfix
Version: 0.2
Summary: Puts curly braces around acronyms in titles in bibtex files.
Home-page: UNKNOWN
Author: Johannes Wienke
Author-email: languitar@semipol.de
License: LGPLv3+
Platform: UNKNOWN
